[
	{
		"name": "Football"
	},
	{
		"name": "Baseball"
	},
	{
		"name": "Rugby"
	},
	{
		"name": "Athlétisme"
	},
	{
		"name": "canoe-kayak"
	},
	{
		"name": "cyclisme"
	},
	{
		"name": "Football américain"
	},
	{
		"name": "Golf"
	},
	{
		"name": "Marathon"
	},
	{
		"name": "Surf"
	},
	{
		"name": "Voile"
	},
	{
		"name": "marche"
	},
	{
		"name": "Automobile"
	},
	{
		"name": "Formule 1"
	},
	{
		"name": "Tennis"
	},
	{
		"name": "Escalade"
	},
	{
		"name": "Volley-ball"
	},
	{
		"name": "Trottinette"
	},
	{
		"name": "Handball"
	},
	{
		"name": "Futsal"
	},
	{
		"name": "Arts martiaux"
	},
	{
		"name": "Badminton"
	},
	{
		"name": "Billard"
	},
	{
		"name": "boxe"
	},
	{
		"name": "Curling"
	},
	{
		"name": "Equitation"
	},
	{
		"name": "gymnastique"
	},
	{
		"name": "Judo"
	},
	{
		"name": "Karaté"
	},
	{
		"name": "Natation"
	},
	{
		"name": "pétanque"
	},
	{
		"name": "Plongeon"
	},
	{
		"name": "Roller"
	},
	{
		"name": "Taekwondo"
	},
	{
		"name": "Water-polo"
	},
	{
		"name": "Snowboard"
	},
	{
		"name": "Ski"
	},
	{
		"name": "Hockey sur glace"
	}
]
